setup.cfg
setup.py
kolyaklimkLab3/__init__.py
kolyaklimkLab3.egg-info/PKG-INFO
kolyaklimkLab3.egg-info/SOURCES.txt
kolyaklimkLab3.egg-info/dependency_links.txt
kolyaklimkLab3.egg-info/not-zip-safe
kolyaklimkLab3.egg-info/top_level.txt
kolyaklimkLab3/MyParser/Constants.py
kolyaklimkLab3/MyParser/Parser.py
kolyaklimkLab3/MyParser/__init__.py
kolyaklimkLab3/MyParser/JsonParser/Constants.py
kolyaklimkLab3/MyParser/JsonParser/Json.py
kolyaklimkLab3/MyParser/JsonParser/__init__.py
kolyaklimkLab3/MyParser/XmlParser/Constants.py
kolyaklimkLab3/MyParser/XmlParser/Xml.py
kolyaklimkLab3/MyParser/XmlParser/__init__.py
kolyaklimkLab3/MySerializer/Factory.py
kolyaklimkLab3/MySerializer/Serializer.py
kolyaklimkLab3/MySerializer/__init__.py