Metadata-Version: 2.1
Name: kolyaklimkLab3
Version: 3.0.0
Summary: # Serializerib
Author-email: kolyaklimk@gmail.com
